library/__init__.py
library/airqoairqloudanalysis.py
airqo_analyzer-0.0.1.dist-info/METADATA
airqo_analyzer-0.0.1.dist-info/WHEEL
airqo_analyzer-0.0.1.dist-info/top_level.txt
airqo_analyzer-0.0.1.dist-info/RECORD
