Metadata-Version: 2.1
Name: airqo-analyzer
Version: 0.0.1
Summary: This is used for analyzing the obtain from IoT AirQo devices
Author: AirQo
Author-email: <gibson@airqo.net>
Keywords: python,IoT,AirQo,data,analysis,insights
Classifier: Development Status :: 3 - Alpha
Classifier: Intended Audience :: Developers
Classifier: Programming Language :: Python :: 3
Classifier: Operating System :: MacOS :: MacOS X
Classifier: Operating System :: Microsoft :: Windows
Classifier: Operating System :: POSIX :: Linux
Requires-Dist: numpy
Requires-Dist: pandas
Requires-Dist: requests
Requires-Dist: pytz
Requires-Dist: python-dateutil
Requires-Dist: beautifulsoup4
Requires-Dist: matplotlib
Requires-Dist: seaborn
Requires-Dist: plotly
Requires-Dist: cufflinks
